crosslang/__init__.py
crosslang/executor.py
crosslang/runners/__init__.py
crosslang/runners/c_runner.py
crosslang/runners/go_runner.py
crosslang/runners/java_runner.py
crosslang/runners/js_runner.py
crosslang/runners/kotlin_runner.py
crosslang/runners/lua_runner.py
crosslang/runners/perl_runner.py
crosslang/runners/php_runner.py
crosslang/runners/ruby_runner.py
crosslang/runners/rust_runner.py
crosslang/runners/scala_runner.py
crosslang/runners/shell_runner.py
python_crosslang-0.1.6.dist-info/LICENSE
python_crosslang-0.1.6.dist-info/METADATA
python_crosslang-0.1.6.dist-info/WHEEL
python_crosslang-0.1.6.dist-info/top_level.txt
python_crosslang-0.1.6.dist-info/RECORD
