Metadata-Version: 2.1
Name: python-crosslang
Version: 0.1.6
Summary: A Python library to run code from multiple programming languages.
Home-page: https://github.com/fl9ppy/crosslang
Author: fl9ppy
Author-email: adi.calinescu16@gmail.com
Classifier: Programming Language :: Python :: 3
Classifier: License :: OSI Approved :: MIT License
Classifier: Operating System :: OS Independent
Requires-Python: >=3.6
License-File: LICENSE
